woeBinningPandas/__init__.py
woeBinningPandas/woebinningpandas.py
woeBinningPandas-1.9.dist-info/LICENSE.txt
woeBinningPandas-1.9.dist-info/METADATA
woeBinningPandas-1.9.dist-info/WHEEL
woeBinningPandas-1.9.dist-info/top_level.txt
woeBinningPandas-1.9.dist-info/RECORD
