Metadata-Version: 2.1
Name: woeBinningPandas
Version: 1.9
Summary: My package from github repo.
Home-page: https://github.com/V1ad98/woeBinningPandas.git
Author: V1ad98
Author-email: 47775603+V1ad98@users.noreply.github.com
License: MIT
Platform: UNKNOWN
Classifier: Development Status :: 3 - Alpha
Classifier: Intended Audience :: Developers
Classifier: Topic :: Software Development :: Build Tools
Classifier: License :: OSI Approved :: MIT License
Classifier: Programming Language :: Python :: 3.7
Requires-Dist: pandas
Requires-Dist: numpy
